jpcleanup/__init__.py
jpcleanup/cell.py
jpcleanup/core.py
jpcleanup/io.py
jp_cleanup-0.1.1.dist-info/METADATA
jp_cleanup-0.1.1.dist-info/WHEEL
jp_cleanup-0.1.1.dist-info/entry_points.txt
jp_cleanup-0.1.1.dist-info/top_level.txt
jp_cleanup-0.1.1.dist-info/RECORD
