Metadata-Version: 2.1
Name: jp-cleanup
Version: 0.1.1
Summary: Cleanup Jupyter Notebook files
Home-page: UNKNOWN
Author: Lars Klitzke
Author-email: Lars.Klitzke@gmail.com
License: GNU GPLv3
Platform: UNKNOWN
Classifier: Programming Language :: Python :: 3
Classifier: Programming Language :: Python :: 3.5
Classifier: Programming Language :: Unix Shell
Classifier: Intended Audience :: Science/Research
Classifier: Intended Audience :: Information Technology
Classifier: Intended Audience :: Manufacturing
Classifier: Topic :: Scientific/Engineering :: Information Analysis
